{
  "optimization_time": "2025-12-21T19:15:40.316388",
  "total_processing_time": 0.973452,
  "vector_optimization": {
    "status": "success",
    "vectors_created": 150,
    "collections_updated": [
      "legal_hierarchy_constitutional_law",
      "legal_hierarchy_basic_law",
      "legal_hierarchy_specific_law",
      "legal_hierarchy_regulations",
      "legal_hierarchy_judicial_interpretation",
      "legal_topic_patent_law",
      "legal_topic_copyright_law",
      "legal_topic_trademark_law",
      "legal_topic_civil_law",
      "legal_topic_criminal_law",
      "legal_topic_administrative_law",
      "legal_topic_commercial_law",
      "legal_topic_labor_law",
      "legal_topic_environmental_law",
      "legal_time_historical",
      "legal_time_current",
      "legal_time_recent"
    ],
    "enhancements_applied": [
      "bge_large_vectors",
      "bert_semantic_enhancement",
      "context_aware_vectors"
    ],
    "processing_time": 0.901859
  },
  "knowledge_graph_expansion": {
    "status": "success",
    "entities_added": 12,
    "relations_added": 8,
    "hierarchies_built": 4,
    "enrichments_applied": [
      "entity_relation_extraction",
      "hierarchy_construction",
      "semantic_associations",
      "entity_linking"
    ],
    "processing_time": 0.010213
  },
  "multimodal_integration": {
    "status": "success",
    "images_processed": 0,
    "pdfs_processed": 0,
    "tables_extracted": 0,
    "charts_extracted": 0,
    "processing_time": 0.0177
  },
  "qa_system_enhancement": {
    "status": "success",
    "qa_pairs_generated": 0,
    "summaries_created": 0,
    "semantic_analyses_performed": 0,
    "enhancements_applied": [
      "qa_pair_generation",
      "document_summarization",
      "semantic_analysis",
      "qa_knowledge_base"
    ],
    "processing_time": 0.043628
  },
  "overall_statistics": {
    "start_time": 