{
  "verification_time": "2025-12-18T09:38:09.193459",
  "princess_name": "小诺·双鱼公主",
  "completeness": 100.0,
  "status_count": {
    "operational": 8,
    "partial": 0,
    "missing": 0,
    "error": 0,
    "checking": 0
  },
  "modules": {
    "perception": {
      "module_name": "感知引擎",
      "status": "operational",
      "details": {
        "engine_exists": true,
        "processors_count": 5,
        "test_result": true
      },
      "capabilities": [
        "InputType.TEXT处理器",
        "InputType.IMAGE处理器",
        "InputType.AUDIO处理器",
        "InputType.VIDEO处理器",
        "InputType.MULTIMODAL处理器"
      ]
    },
    "cognition": {
      "module_name": "认知引擎",
      "status": "operational",
      "details": {
        "engine_exists": true,
        "test_result": true
      },
      "capabilities": []
    },
    "execution": {
      "module_name": "执行引擎",
      "status": "operational",
      "details": {
        "engine_exists": true,
        "test_result": true
      },
      "capabilities": []
    },
    "learning": {
      "module_name": "学习引擎",
      "status": "operational",
      "details": {
        "engine_exists": true,
        "learning_capability": true,
        "test_result": true
      },
      "capabilities": [
        "自适应学习"
      ]
    },
    "communication": {
      "module_name": "通讯引擎",
      "status": "operational",
      "details": {
        "engine_exists": true,
        "channels_count": 2,
        "test_result": true
      },
      "capabilities": [
        "多通道通讯"
      ]
    },
    "evaluation": {
      "module_name": "评估引擎",
      "status": "operational",
      "details": {
        "engine_exists": true,
        "test_result": true
      },
      "capabilities": []
    },
    "memory": {
      "module_name": "记忆系统",
      "status": "operational",
      "details": {
        "memory_exists": true,
        "vector_memory": true,
        "test_result": true
      },
      "capabilities": [
        "向量记忆"
      ]
    },
    "knowledge": {
      "module_name": "知识管理器",
      "status": "operational",
      "details": {
        "knowledge_exists": true,
        "patent_system": true,
        "test_result": true
      },
      "capabilities": [
        "专利分析"
      ]
    }
  }
}